MANIFEST.in
setup.cfg
setup.py
chemkin_g10/__init__.py
chemkin_g10/chemkin.py
chemkin_g10/computation.py
chemkin_g10/db.py
chemkin_g10/nasa.sqlite
chemkin_g10/simulator.py
chemkin_g10/thermo.py
chemkin_g10.egg-info/PKG-INFO
chemkin_g10.egg-info/SOURCES.txt
chemkin_g10.egg-info/dependency_links.txt
chemkin_g10.egg-info/requires.txt
chemkin_g10.egg-info/top_level.txt
tests/__init__.py
tests/test_chemkin.py
tests/test_computation.py
tests/test_db.py
tests/data/db/nasa.sqlite
tests/data/db/thermo.sqlite
tests/data/xml/rxns_irreversible.xml
tests/data/xml/rxns_mixed.xml
tests/data/xml/rxns_reversible.xml
tests/data/xml/rxns_short_1.xml
tests/data/xml/rxns_short_2.xml
tests/data/xml/thermo.xml