Metadata-Version: 1.0
Name: chemkin-g10
Version: 0.70
Summary: A chemical kinetics library
Home-page: https://github.com/CS207Team10/cs207-FinalProject
Author: Hidenori Tanaka, Jiachen Song, Xiangru Shu
Author-email: jsong1@g.harvard.edu
License: MIT
Platform: UNKNOWN
